codrone_edu/__init__.py
codrone_edu/__main__.py
codrone_edu/crc.py
codrone_edu/drone.py
codrone_edu/errors.py
codrone_edu/protocol.py
codrone_edu/receiver.py
codrone_edu/storage.py
codrone_edu/swarm.py
codrone_edu/system.py
codrone_edu/data/black.txt
codrone_edu/data/blue.txt
codrone_edu/data/green.txt
codrone_edu/data/lightblue.txt
codrone_edu/data/purple.txt
codrone_edu/data/red.txt
codrone_edu/data/white.txt
codrone_edu/data/yellow.txt
codrone_edu/tools/__init__.py
codrone_edu/tools/interrupter.py
codrone_edu/tools/parser.py
codrone_edu/tools/transformer.py
codrone_edu/tools/update.py
codrone_edu-2.6.dist-info/METADATA
codrone_edu-2.6.dist-info/WHEEL
codrone_edu-2.6.dist-info/top_level.txt
codrone_edu-2.6.dist-info/RECORD
